{
  "showTitles": [
    "Re:ZERO -Starting Life in Another World-",
    "Re:Zero kara Hajimeru Isekai Seikatsu",
    "Re:ゼロから始める異世界生活"
  ],
  "charNames": [
    "Roswaal L. Mathers",
    "ロズワール・Ｌ・メイザース"
  ],
  "character": {
    "name": {
      "first": "Roswaal L.",
      "last": "Mathers",
      "full": "Roswaal L. Mathers",
      "native": "ロズワール・Ｌ・メイザース"
    },
    "description": "<p>The lord of the Roswaal Mansion and a descendant of the original Roswaal.</p>\n<p>~!It is later revealed that he is in fact the original Roswaal, Roswaal A. Mathers, who has been possessing his descendants' bodies.!~</p>\n",
    "image": {
      "large": "https://s4.anilist.co/file/anilistcdn/character/large/b90182-jZjQxB1bIKrU.jpg",
      "medium": "https://s4.anilist.co/file/anilistcdn/character/medium/b90182-jZjQxB1bIKrU.jpg"
    }
  }
}